README.md
setup.cfg
setup.py
pytorchUtils/LiveFigure.py
pytorchUtils/Pipeline.py
pytorchUtils/__init__.py
pytorchUtils.egg-info/PKG-INFO
pytorchUtils.egg-info/SOURCES.txt
pytorchUtils.egg-info/dependency_links.txt
pytorchUtils.egg-info/requires.txt
pytorchUtils.egg-info/top_level.txt
pytorchUtils/models/BaseClassificationModel.py
pytorchUtils/models/ResNet.py
pytorchUtils/models/__init__.py
pytorchUtils/models/pretrained/Pretrained.py
pytorchUtils/models/pretrained/__init__.py