Metadata-Version: 1.1
Name: pytorchUtils
Version: 0.0.3
Summary: Some utility classes for use with pytorch
Home-page: https://github.com/alex-bene/pytorch-utils
Author: Alexandros Benetatos
Author-email: alexandrosbene@gmail.com
License: MIT
Download-URL: https://github.com/alex-bene/pytorch-utils/archive/v0.0.2-beta.tar.gz
Keywords: pytorch,utilities 
Platform: UNKNOWN
Classifier: Development Status :: 4 - Beta
Classifier: Intended Audience :: Developers
Classifier: Topic :: Software Development :: Build Tools
Classifier: License :: OSI Approved :: MIT License
Classifier: Programming Language :: Python :: 3
Classifier: Operating System :: OS Independent
